LICENSE
MANIFEST.in
README.md
requirements.txt
setup.py
examples/README.md
examples/multi_page/Makefile
examples/multi_page/README.md
examples/multi_page/lib.c
examples/multi_page/lib.h
examples/multi_page/main.tex
examples/multi_page/user.c
examples/simple/Makefile
examples/simple/README.md
examples/simple/hello_simple.c
examples/simple/ignore.txt
pycflow2dot/__init__.py
pycflow2dot/_version.py
pycflow2dot/pycflow2dot.py
pycflow2dot.egg-info/PKG-INFO
pycflow2dot.egg-info/SOURCES.txt
pycflow2dot.egg-info/dependency_links.txt
pycflow2dot.egg-info/entry_points.txt
pycflow2dot.egg-info/requires.txt
pycflow2dot.egg-info/top_level.txt
tests/Makefile
tests/README.md
tests/basic_test.c