Metadata-Version: 2.1
Name: pycflow2dot
Version: 0.2.3
Summary: Create C call graphs from multiple source files using Cflow, producing linked PDF.
Home-page: https://github.com/johnyf/pycflow2dot
Author: Ioannis Filippidis
Author-email: jfilippidis@gmail.com
License: GPLv3
Keywords: c,call graph,control flow,dot,latex,cflow
Platform: UNKNOWN
Classifier: Development Status :: 2 - Pre-Alpha
Classifier: Intended Audience :: Developers
Classifier: License :: OSI Approved :: GNU General Public License v3 or later (GPLv3+)
Classifier: Operating System :: OS Independent
Classifier: Programming Language :: Python
Classifier: Programming Language :: Python :: 2.7
Classifier: Programming Language :: Python :: 3
Classifier: Programming Language :: Python :: 3.5
Classifier: Programming Language :: Python :: 3.6
Classifier: Programming Language :: Python :: 3.7
Classifier: Programming Language :: Python :: 3.8
Classifier: Programming Language :: Python :: 3.9
Classifier: Topic :: Software Development
